dataherald/__init__.py
dataherald/_base_client.py
dataherald/_client.py
dataherald/_compat.py
dataherald/_constants.py
dataherald/_exceptions.py
dataherald/_files.py
dataherald/_models.py
dataherald/_qs.py
dataherald/_resource.py
dataherald/_response.py
dataherald/_streaming.py
dataherald/_types.py
dataherald/_version.py
dataherald/py.typed
dataherald/_utils/__init__.py
dataherald/_utils/_logs.py
dataherald/_utils/_proxy.py
dataherald/_utils/_streams.py
dataherald/_utils/_sync.py
dataherald/_utils/_transform.py
dataherald/_utils/_typing.py
dataherald/_utils/_utils.py
dataherald/lib/.keep
dataherald/resources/__init__.py
dataherald/resources/engine.py
dataherald/resources/finetunings.py
dataherald/resources/generations.py
dataherald/resources/golden_sqls.py
dataherald/resources/heartbeat.py
dataherald/resources/nl_generations.py
dataherald/resources/table_descriptions.py
dataherald/resources/database_connections/__init__.py
dataherald/resources/database_connections/database_connections.py
dataherald/resources/database_connections/drivers.py
dataherald/resources/instructions/__init__.py
dataherald/resources/instructions/first.py
dataherald/resources/instructions/instructions.py
dataherald/resources/prompts/__init__.py
dataherald/resources/prompts/prompts.py
dataherald/resources/prompts/sql_generations.py
dataherald/resources/sql_generations/__init__.py
dataherald/resources/sql_generations/nl_generations.py
dataherald/resources/sql_generations/sql_generations.py
dataherald/types/__init__.py
dataherald/types/database_connection_create_params.py
dataherald/types/database_connection_list_response.py
dataherald/types/database_connection_update_params.py
dataherald/types/db_connection_response.py
dataherald/types/finetuning_create_params.py
dataherald/types/finetuning_list_params.py
dataherald/types/finetuning_list_response.py
dataherald/types/finetuning_response.py
dataherald/types/generation_list_item.py
dataherald/types/generation_list_params.py
dataherald-0.20.0.dist-info/METADATA
dataherald-0.20.0.dist-info/WHEEL
dataherald-0.20.0.dist-info/licenses/LICENSE
dataherald-0.20.0.dist-info/RECORD
